crs_load_testing/Authorize.py
crs_load_testing/Functionality.py
crs_load_testing/__init__.py
crs_load_testing-1.0.4.dist-info/METADATA
crs_load_testing-1.0.4.dist-info/WHEEL
crs_load_testing-1.0.4.dist-info/top_level.txt
crs_load_testing-1.0.4.dist-info/RECORD
