Metadata-Version: 2.1
Name: crs-load-testing
Version: 1.0.4
Summary: package for CRS load testing
Author: srujan
Author-email: srujan.gopi@kroll.com
License: UNKNOWN
Platform: UNKNOWN
Classifier: Programming Language :: Python :: 3
Classifier: License :: OSI Approved :: MIT License
Classifier: Operating System :: OS Independent
Requires-Python: >=3.6
